{
    "name": "autosave",
    "icon": null,
    "attributes": {
        "isPaused": false,
        "isElementCreating": false,
        "isMoving": false,
        "isScreenMoving": false,
        "isMassSetting": false,
        "isCircularVelocityGetting": false,
        "isCircularVelocityDirectionAnticlockwise": true,
        "isCtrlPressing": false,
        "isEditing": false,
        "isElementControlling": false,
        "isPressed": false,
        "isDragging": false,
        "isCelestialBodyMode": false,
        "isModeChangingNaturally": false,
        "isChatting": false,
        "icon": "",
        "screenSize": [
            1920,
            1080
        ],
        "mousePos": [
            1032,
            301
        ],
        "ratio": 5,
        "lastRatio": 5,
        "minLimitRatio": 1,
        "maxLimitRatio": 15,
        "x": 192.0,
        "y": 216.0,
        "lastX": 192.0,
        "lastY": 20000000.0,
        "currentTime": 1757173448.0441542,
        "lastTime": 1757173448.0118542,
        "fpsAverage": 31.066924098699836,
        "fpsMinimum": 25.171512761884184,
        "rightMove": 0,
        "upMove": 0,
        "speed": 1,
        "circularVelocityFactor": 1,
        "isFloorIllegal": false,
        "background": "lightgrey",
        "tempFrames": 0,
        "optionsList": [
            {
                "type": "ball",
                "name": "弹力球",
                "attrs": [
                    {
                        "type": "mass",
                        "value": 1,
                        "min": 0.1,
                        "max": 32767
                    },
                    {
                        "type": "radius",
                        "value": 5,
                        "min": 1,
                        "max": 1024
                    },
                    {
                        "type": "color",
                        "value": "RED",
                        "min": "#000000",
                        "max": "#FFFFFF"
                    }
                ],
                "controlOptions": [
                    {
                        "type": "attrEditor"
                    },
                    {
                        "type": "copy"
                    },
                    {
                        "type": "delete"
                    },
                    {
                        "type": "follow"
                    },
                    {
                        "type": "showInfo"
                    },
                    {
                        "type": "addVelocity"
                    },
                    {
                        "type": "clearVelocity"
                    },
                    {
                        "type": "addForce"
                    },
                    {
                        "type": "clearForce"
                    }
                ]
            },
            {
                "type": "wall",
                "name": "墙",
                "attrs": [
                    {
                        "type": "color",
                        "value": "BLUE",
                        "min": "#000000",
                        "max": "#FFFFFF"
                    }
                ],
                "controlOptions": [
                    {
                        "type": "attrEditor"
                    },
                    {
                        "type": "copy"
                    },
                    {
                        "type": "delete"
                    }
                ]
            },
            {
                "type": "rope",
                "name": "绳索",
                "attrs": [
                    {
                        "type": "lengthLimit",
                        "value": "0",
                        "min": "0",
                        "max": "2147483647"
                    }
                ],
                "controlOptions": [
                    {
                        "type": "attrEditor"
                    },
                    {
                        "type": "delete"
                    }
                ]
            },
            {
                "type": "spring",
                "name": "弹簧",
                "attrs": [
                    {
                        "type": "lengthLimit",
                        "value": "0",
                        "min": "0",
                        "max": "2147483647"
                    }
                ],
                "controlOptions": [
                    {
                        "type": "attrEditor"
                    },
                    {
                        "type": "delete"
                    }
                ]
            },
            {
                "type": "rod",
                "name": "轻杆",
                "attrs": [
                    {
                        "type": "lengthLimit",
                        "value": "0",
                        "min": "0",
                        "max": "2147483647"
                    }
                ],
                "controlOptions": [
                    {
                        "type": "attrEditor"
                    },
                    {
                        "type": "delete"
                    }
                ]
            }
        ],
        "environmentOptions": [
            {
                "type": "gravity",
                "value": 1.0,
                "min": 0.0,
                "max": 1000.0
            },
            {
                "type": "airResistance",
                "value": 1.0,
                "min": 0.0,
                "max": 100.0
            },
            {
                "type": "collisionFactor",
                "value": 1.0,
                "min": 0.0,
                "max": 1.0
            },
            {
                "type": "mode",
                "value": 0,
                "min": 0,
                "max": 1
            }
        ],
        "translation": {
            "radius": "半径",
            "mass": "质量",
            "color": "颜色",
            "lengthLimit": "长度限制",
            "gravity": "重力加速度",
            "airResistance": "空气阻力",
            "collisionFactor": "碰撞系数",
            "mode": "模式(按P键可切换)",
            "attrEditor": "属性编辑",
            "copy": "复制",
            "delete": "删除",
            "showInfo": "显示信息",
            "follow": "视角跟随",
            "addVelocity": "添加速度",
            "clearVelocity": "清除速度",
            "addForce": "添加力",
            "clearForce": "清除所有外力"
        },
        "environmentOptionsCopy": [
            {
                "type": "gravity",
                "value": 1.0,
                "min": 0.0,
                "max": 1000.0
            },
            {
                "type": "airResistance",
                "value": 1.0,
                "min": 0.0,
                "max": 100.0
            },
            {
                "type": "collisionFactor",
                "value": 1.0,
                "min": 0.0,
                "max": 1.0
            },
            {
                "type": "mode",
                "value": 0,
                "min": 0,
                "max": 1
            }
        ]
    },
    "elements": {
        "ball": [
            {
                "type": "ball",
                "position": [
                    -2657.9551841239445,
                    -33.86992036865036
                ],
                "id": 2511337547120,
                "mass": 1.0,
                "radius": 9.0,
                "color": "RED",
                "velocity": [
                    -149.22514915123375,
                    186.07388213627283
                ],
                "acceleration": [
                    0,
                    98.1
                ]
            },
            {
                "type": "ball",
                "position": [
                    -337.1971950370924,
                    -121.92360731344992
                ],
                "id": 2511337495424,
                "mass": 1.0,
                "radius": 9.0,
                "color": "RED",
                "velocity": [
                    -83.60620956075427,
                    4.087374629531157
                ],
                "acceleration": [
                    0,
                    98.1
                ]
            },
            {
                "type": "ball",
                "position": [
                    4176.415862940097,
                    -89.4314724274176
                ],
                "id": 2511337569792,
                "mass": 1.0,
                "radius": 9.0,
                "color": "RED",
                "velocity": [
                    214.85436658725502,
                    34.65642260398036
                ],
                "acceleration": [
                    0,
                    98.1
                ]
            },
            {
                "type": "ball",
                "position": [
                    -7679.563410319877,
                    -318.8884892738106
                ],
                "id": 2511337566672,
                "mass": 1.0,
                "radius": 9.0,
                "color": "RED",
                "velocity": [
                    -433.1732571222033,
                    -91.32728065436345
                ],
                "acceleration": [
                    0,
                    98.1
                ]
            },
            {
                "type": "ball",
                "position": [
                    7743.965744533686,
                    -313.3321562981297
                ],
                "id": 2511337618944,
                "mass": 1.0,
                "radius": 9.0,
                "color": "RED",
                "velocity": [
                    430.0039801340469,
                    -111.03198442538817
                ],
                "acceleration": [
                    0,
                    98.1
                ]
            },
            {
                "type": "ball",
                "position": [
                    -6851.395587245777,
                    -85.14806501689527
                ],
                "id": 2511337626736,
                "mass": 1.0,
                "radius": 9.0,
                "color": "RED",
                "velocity": [
                    -379.781043174552,
                    -11.109059796652023
                ],
                "acceleration": [
                    0,
                    98.1
                ]
            },
            {
                "type": "ball",
                "position": [
                    5314.759473518138,
                    -89.49664582124413
                ],
                "id": 2511337555872,
                "mass": 1.0,
                "radius": 9.0,
                "color": "RED",
                "velocity": [
                    301.51528993003706,
                    211.9286148366637
                ],
                "acceleration": [
                    0,
                    98.1
                ]
            },
            {
                "type": "ball",
                "position": [
                    4643.19129184676,
                    -22.83985509811751
                ],
                "id": 2511337570080,
                "mass": 1.0,
                "radius": 9.0,
                "color": "RED",
                "velocity": [
                    276.81948048111894,
                    36.20895785379401
                ],
                "acceleration": [
                    0,
                    98.1
                ]
            },
            {
                "type": "ball",
                "position": [
                    -4008.865801295715,
                    -23.578720165532438
                ],
                "id": 2511337560816,
                "mass": 1.0,
                "radius": 9.0,
                "color": "RED",
                "velocity": [
                    -226.15771802092317,
                    67.28017357231509
                ],
                "acceleration": [
                    0,
                    98.1
                ]
            },
            {
                "type": "ball",
                "position": [
                    2210.302882322984,
                    -24.986108226002123
                ],
                "id": 2511337647968,
                "mass": 1.0,
                "radius": 9.0,
                "color": "RED",
                "velocity": [
                    98.34427248964047,
                    -58.60823774308207
                ],
                "acceleration": [
                    0,
                    98.1
                ]
            },
            {
                "type": "ball",
                "position": [
                    -1905.0217735842004,
                    -73.3407592559006
                ],
                "id": 2511337503344,
                "mass": 1.0,
                "radius": 9.0,
                "color": "RED",
                "velocity": [
                    -66.77091807078887,
                    46.77687885496142
                ],
                "acceleration": [
                    0,
                    98.1
                ]
            },
            {
                "type": "ball",
                "position": [
                    -2633.4691108830016,
                    -21.36082609094149
                ],
                "id": 2511337545632,
                "mass": 1.0,
                "radius": 9.0,
                "color": "RED",
                "velocity": [
                    -131.61876736505582,
                    16.689287506355058
                ],
                "acceleration": [
                    0,
                    98.1
                ]
            },
            {
                "type": "ball",
                "position": [
                    6591.332721738278,
                    -53.34069020019759
                ],
                "id": 2511337501616,
                "mass": 1.0,
                "radius": 9.0,
                "color": "RED",
                "velocity": [
                    380.156463841291,
                    38.22216868261644
                ],
                "acceleration": [
                    0,
                    98.1
                ]
            },
            {
                "type": "ball",
                "position": [
                    -5428.5665805508315,
                    -27.134777738765965
                ],
                "id": 2511337666848,
                "mass": 1.0,
                "radius": 9.0,
                "color": "RED",
                "velocity": [
                    -328.4229604674599,
                    164.53413331369677
                ],
                "acceleration": [
                    0,
                    98.1
                ]
            },
            {
                "type": "ball",
                "position": [
                    2753.1005443607987,
                    -76.56782419910769
                ],
                "id": 2511337666944,
                "mass": 1.0,
                "radius": 9.0,
                "color": "RED",
                "velocity": [
                    157.05392675564272,
                    120.25344693527745
                ],
                "acceleration": [
                    0,
                    98.1
                ]
            },
            {
                "type": "ball",
                "position": [
                    4749.8311140372425,
                    -73.66030934500978
                ],
                "id": 2511337664016,
                "mass": 1.0,
                "radius": 9.0,
                "color": "RED",
                "velocity": [
                    262.28482621427344,
                    63.719273353668584
                ],
                "acceleration": [
                    0,
                    98.1
                ]
            },
            {
                "type": "ball",
                "position": [
                    -186.32670499028822,
                    -23.9551582404697
                ],
                "id": 2511337558272,
                "mass": 1.0,
                "radius": 9.0,
                "color": "RED",
                "velocity": [
                    40.26349576178179,
                    -48.727814542930226
                ],
                "acceleration": [
                    0,
                    98.1
                ]
            },
            {
                "type": "ball",
                "position": [
                    1210.4691836094212,
                    -26.35389099780316
                ],
                "id": 2511337618752,
                "mass": 1.0,
                "radius": 9.0,
                "color": "RED",
                "velocity": [
                    138.27962531937106,
                    -11.297556999752338
                ],
                "acceleration": [
                    0,
                    98.1
                ]
            },
            {
                "type": "ball",
                "position": [
                    -587.291331812956,
                    -593.7180929238497
                ],
                "id": 2511337667952,
                "mass": 1.0,
                "radius": 9.0,
                "color": "RED",
                "velocity": [
                    4.5452318143720065,
                    -8.394485769805723
                ],
                "acceleration": [
                    0,
                    98.1
                ]
            },
            {
                "type": "ball",
                "position": [
                    -149.52042030076285,
                    -20.61786892089388
                ],
                "id": 2511337504448,
                "mass": 1.0,
                "radius": 9.0,
                "color": "RED",
                "velocity": [
                    -3.454855063136449,
                    106.65341833987134
                ],
                "acceleration": [
                    0,
                    98.1
                ]
            },
            {
                "type": "ball",
                "position": [
                    3254.1235841172534,
                    -40.26067612170975
                ],
                "id": 2511337668192,
                "mass": 1.0,
                "radius": 9.0,
                "color": "RED",
                "velocity": [
                    135.27309200396783,
                    21.267076349930463
                ],
                "acceleration": [
                    0,
                    98.1
                ]
            },
            {
                "type": "ball",
                "position": [
                    -5679.991776218485,
                    -115.32682147839438
                ],
                "id": 2511337667424,
                "mass": 1.0,
                "radius": 9.0,
                "color": "RED",
                "velocity": [
                    -316.4621051557434,
                    -76.74016327488897
                ],
                "acceleration": [
                    0,
                    98.1
                ]
            },
            {
                "type": "ball",
                "position": [
                    2771.449605763157,
                    -33.911971584725826
                ],
                "id": 2511337496624,
                "mass": 1.0,
                "radius": 9.0,
                "color": "RED",
                "velocity": [
                    199.1246265455173,
                    72.91503259507746
                ],
                "acceleration": [
                    0,
                    98.1
                ]
            },
            {
                "type": "ball",
                "position": [
                    -1394.3634236204143,
                    -32.538347795014246
                ],
                "id": 2511337636880,
                "mass": 1.0,
                "radius": 9.0,
                "color": "RED",
                "velocity": [
                    -70.37353817399688,
                    22.99592564651025
                ],
                "acceleration": [
                    0,
                    98.1
                ]
            },
            {
                "type": "ball",
                "position": [
                    -3393.8735490310773,
                    -37.56150999769609
                ],
                "id": 2511337502672,
                "mass": 1.0,
                "radius": 9.0,
                "color": "RED",
                "velocity": [
                    -191.5385975613005,
                    24.05354308672525
                ],
                "acceleration": [
                    0,
                    98.1
                ]
            },
            {
                "type": "ball",
                "position": [
                    5227.108877064014,
                    -321.92557632126193
                ],
                "id": 2511337499264,
                "mass": 1.0,
                "radius": 9.0,
                "color": "RED",
                "velocity": [
                    283.2227203885245,
                    -8.913689722298049
                ],
                "acceleration": [
                    0,
                    98.1
                ]
            },
            {
                "type": "ball",
                "position": [
                    -5349.595013554365,
                    -24.299174845054456
                ],
                "id": 2511337497488,
                "mass": 1.0,
                "radius": 9.0,
                "color": "RED",
                "velocity": [
                    -340.8260916885709,
                    -15.240145159440075
                ],
                "acceleration": [
                    0,
                    98.1
                ]
            },
            {
                "type": "ball",
                "position": [
                    1069.2555802516263,
                    -20.136382323613333
                ],
                "id": 2511337665984,
                "mass": 1.0,
                "radius": 9.0,
                "color": "RED",
                "velocity": [
                    81.99758365112798,
                    -32.96469904333639
                ],
                "acceleration": [
                    0,
                    98.1
                ]
            },
            {
                "type": "ball",
                "position": [
                    5040.638150059146,
                    -44.63806115862592
                ],
                "id": 2511337696880,
                "mass": 1.0,
                "radius": 9.0,
                "color": "RED",
                "velocity": [
                    306.5473232629003,
                    66.50548254597999
                ],
                "acceleration": [
                    0,
                    98.1
                ]
            },
            {
                "type": "ball",
                "position": [
                    -3071.36156266322,
                    -21.660232977212587
                ],
                "id": 2511337665648,
                "mass": 1.0,
                "radius": 9.0,
                "color": "RED",
                "velocity": [
                    -169.777389382814,
                    37.5894885927669
                ],
                "acceleration": [
                    0,
                    98.1
                ]
            },
            {
                "type": "ball",
                "position": [
                    3364.060133590595,
                    -112.1831522478727
                ],
                "id": 2511337664352,
                "mass": 1.0,
                "radius": 9.0,
                "color": "RED",
                "velocity": [
                    222.84366720482035,
                    -92.76026341410285
                ],
                "acceleration": [
                    0,
                    98.1
                ]
            },
            {
                "type": "ball",
                "position": [
                    -1769.0480065455301,
                    -19.00051452264073
                ],
                "id": 2511337498304,
                "mass": 1.0,
                "radius": 9.0,
                "color": "RED",
                "velocity": [
                    -119.38803793545837,
                    -2.213688553767393
                ],
                "acceleration": [
                    0,
                    98.1
                ]
            },
            {
                "type": "ball",
                "position": [
                    -2964.8572893067912,
                    -146.36377602031976
                ],
                "id": 2511337499936,
                "mass": 1.0,
                "radius": 9.0,
                "color": "RED",
                "velocity": [
                    -192.18412149284566,
                    125.04492706223259
                ],
                "acceleration": [
                    0,
                    98.1
                ]
            },
            {
                "type": "ball",
                "position": [
                    7500.801559707746,
                    -35.77486483431165
                ],
                "id": 2511337663584,
                "mass": 1.0,
                "radius": 9.0,
                "color": "RED",
                "velocity": [
                    428.9700615908218,
                    -6.258680579058208
                ],
                "acceleration": [
                    0,
                    98.1
                ]
            },
            {
                "type": "ball",
                "position": [
                    -4761.984363309717,
                    -324.40394601160614
                ],
                "id": 2511337503728,
                "mass": 1.0,
                "radius": 9.0,
                "color": "RED",
                "velocity": [
                    -265.0203025937475,
                    -37.33962599479004
                ],
                "acceleration": [
                    0,
                    98.1
                ]
            },
            {
                "type": "ball",
                "position": [
                    1679.4722788750553,
                    -75.9903137747752
                ],
                "id": 2511337691264,
                "mass": 1.0,
                "radius": 9.0,
                "color": "RED",
                "velocity": [
                    100.57495121093126,
                    73.70599563104157
                ],
                "acceleration": [
                    0,
                    98.1
                ]
            },
            {
                "type": "ball",
                "position": [
                    598.9455543420315,
                    -75.20886981843805
                ],
                "id": 2511337502240,
                "mass": 1.0,
                "radius": 9.0,
                "color": "RED",
                "velocity": [
                    30.70224248693791,
                    39.4751543076664
                ],
                "acceleration": [
                    0,
                    98.1
                ]
            },
            {
                "type": "ball",
                "position": [
                    -4359.262819249046,
                    -19.275666756318543
                ],
                "id": 2511337663200,
                "mass": 1.0,
                "radius": 9.0,
                "color": "RED",
                "velocity": [
                    -262.37999140612874,
                    -72.96512219513528
                ],
                "acceleration": [
                    0,
                    98.1
                ]
            },
            {
                "type": "ball",
                "position": [
                    4310.189006144791,
                    -108.48886151405712
                ],
                "id": 2511337664256,
                "mass": 1.0,
                "radius": 9.0,
                "color": "RED",
                "velocity": [
                    272.6210638739568,
                    -31.39070838427942
                ],
                "acceleration": [
                    0,
                    98.1
                ]
            },
            {
                "type": "ball",
                "position": [
                    -4110.665047389831,
                    -116.48712497015268
                ],
                "id": 2511337699712,
                "mass": 1.0,
                "radius": 9.0,
                "color": "RED",
                "velocity": [
                    -213.85129607400086,
                    -30.670999364986542
                ],
                "acceleration": [
                    0,
                    98.1
                ]
            },
            {
                "type": "ball",
                "position": [
                    -2411.1099613883703,
                    -124.69937124073408
                ],
                "id": 2511337698272,
                "mass": 1.0,
                "radius": 9.0,
                "color": "RED",
                "velocity": [
                    -219.2481520814426,
                    38.45093519386722
                ],
                "acceleration": [
                    0,
                    98.1
                ]
            },
            {
                "type": "ball",
                "position": [
                    747.4767565149551,
                    -39.21412296876831
                ],
                "id": 2511337666464,
                "mass": 1.0,
                "radius": 9.0,
                "color": "RED",
                "velocity": [
                    43.81508102670013,
                    -52.12833596536387
                ],
                "acceleration": [
                    0,
                    98.1
                ]
            },
            {
                "type": "ball",
                "position": [
                    -3315.400065308082,
                    -25.833310221231535
                ],
                "id": 2511337562544,
                "mass": 1.0,
                "radius": 9.0,
                "color": "RED",
                "velocity": [
                    -232.30368180603682,
                    -37.95360402671731
                ],
                "acceleration": [
                    0,
                    98.1
                ]
            },
            {
                "type": "ball",
                "position": [
                    1941.998053396259,
                    -41.55196938970969
                ],
                "id": 2511337700720,
                "mass": 1.0,
                "radius": 9.0,
                "color": "RED",
                "velocity": [
                    94.80460960508624,
                    -21.546675231043658
                ],
                "acceleration": [
                    0,
                    98.1
                ]
            },
            {
                "type": "ball",
                "position": [
                    2555.286856379902,
                    -28.075286843875542
                ],
                "id": 2511337689584,
                "mass": 1.0,
                "radius": 9.0,
                "color": "RED",
                "velocity": [
                    197.1403508785143,
                    18.048008307283588
                ],
                "acceleration": [
                    0,
                    98.1
                ]
            },
            {
                "type": "ball",
                "position": [
                    -2497.8837284887295,
                    -19.0006001584256
                ],
                "id": 2511337693136,
                "mass": 1.0,
                "radius": 9.0,
                "color": "RED",
                "velocity": [
                    -86.29551399233206,
                    -2.3890361077264646
                ],
                "acceleration": [
                    0,
                    98.1
                ]
            },
            {
                "type": "ball",
                "position": [
                    4964.489172346191,
                    -30.969630489670077
                ],
                "id": 2511337692704,
                "mass": 1.0,
                "radius": 9.0,
                "color": "RED",
                "velocity": [
                    267.8074586076007,
                    -90.49433419204837
                ],
                "acceleration": [
                    0,
                    98.1
                ]
            },
            {
                "type": "ball",
                "position": [
                    -2401.9174405122167,
                    -22.062183681763585
                ],
                "id": 2511337700864,
                "mass": 1.0,
                "radius": 9.0,
                "color": "RED",
                "velocity": [
                    -202.16444273030706,
                    76.40677581531577
                ],
                "acceleration": [
                    0,
                    98.1
                ]
            },
            {
                "type": "ball",
                "position": [
                    -64.60411221301626,
                    -51.10031189777634
                ],
                "id": 2511337700624,
                "mass": 1.0,
                "radius": 9.0,
                "color": "RED",
                "velocity": [
                    -32.57582366497692,
                    64.15174607187227
                ],
                "acceleration": [
                    0,
                    98.1
                ]
            },
            {
                "type": "ball",
                "position": [
                    907.0955889357241,
                    -25.38455492340906
                ],
                "id": 2511337690544,
                "mass": 1.0,
                "radius": 9.0,
                "color": "RED",
                "velocity": [
                    51.066877406993385,
                    -34.07569838588471
                ],
                "acceleration": [
                    0,
                    98.1
                ]
            },
            {
                "type": "ball",
                "position": [
                    -2312.643529589132,
                    -80.97095139576618
                ],
                "id": 2511337692032,
                "mass": 1.0,
                "radius": 9.0,
                "color": "RED",
                "velocity": [
                    -46.3055136326611,
                    97.21910610161935
                ],
                "acceleration": [
                    0,
                    98.1
                ]
            },
            {
                "type": "ball",
                "position": [
                    2380.1569928882464,
                    -111.19670999512364
                ],
                "id": 2511337502384,
                "mass": 1.0,
                "radius": 9.0,
                "color": "RED",
                "velocity": [
                    120.83088456762887,
                    -34.22661417192823
                ],
                "acceleration": [
                    0,
                    98.1
                ]
            },
            {
                "type": "ball",
                "position": [
                    -640.9793911650546,
                    -27.387113168183227
                ],
                "id": 2511337695968,
                "mass": 1.0,
                "radius": 9.0,
                "color": "RED",
                "velocity": [
                    -90.84661272814914,
                    -46.873098422203796
                ],
                "acceleration": [
                    0,
                    98.1
                ]
            },
            {
                "type": "ball",
                "position": [
                    1461.3692162055618,
                    -57.46904498137581
                ],
                "id": 2511337498688,
                "mass": 1.0,
                "radius": 9.0,
                "color": "RED",
                "velocity": [
                    156.04075921353214,
                    65.33174846708773
                ],
                "acceleration": [
                    0,
                    98.1
                ]
            },
            {
                "type": "ball",
                "position": [
                    3376.823990979871,
                    -40.663116209483924
                ],
                "id": 2511337694192,
                "mass": 1.0,
                "radius": 9.0,
                "color": "RED",
                "velocity": [
                    195.42030248537512,
                    4.845760088854733
                ],
                "acceleration": [
                    0,
                    98.1
                ]
            },
            {
                "type": "ball",
                "position": [
                    -121.90411932246369,
                    -25.12838406968204
                ],
                "id": 2511337698608,
                "mass": 1.0,
                "radius": 9.0,
                "color": "RED",
                "velocity": [
                    39.07220066773739,
                    -59.121934812061596
                ],
                "acceleration": [
                    0,
                    98.1
                ]
            },
            {
                "type": "ball",
                "position": [
                    1856.9307212486508,
                    -80.12216471738272
                ],
                "id": 2511337504640,
                "mass": 1.0,
                "radius": 9.0,
                "color": "RED",
                "velocity": [
                    98.700121960195,
                    -107.46480957200004
                ],
                "acceleration": [
                    0,
                    98.1
                ]
            },
            {
                "type": "ball",
                "position": [
                    3886.10422908685,
                    -68.41418344909322
                ],
                "id": 2511337668096,
                "mass": 1.0,
                "radius": 9.0,
                "color": "RED",
                "velocity": [
                    326.0678037549998,
                    4.498686805917209
                ],
                "acceleration": [
                    0,
                    98.1
                ]
            },
            {
                "type": "ball",
                "position": [
                    -1594.9329166608575,
                    -60.90403922239524
                ],
                "id": 2511337503440,
                "mass": 1.0,
                "radius": 9.0,
                "color": "RED",
                "velocity": [
                    -162.88264013242522,
                    64.26924008184423
                ],
                "acceleration": [
                    0,
                    98.1
                ]
            },
            {
                "type": "ball",
                "position": [
                    129.62225487734878,
                    -21.860601109658543
                ],
                "id": 2511337699472,
                "mass": 1.0,
                "radius": 9.0,
                "color": "RED",
                "velocity": [
                    -10.866581214520501,
                    -42.319071423119375
                ],
                "acceleration": [
                    0,
                    98.1
                ]
            },
            {
                "type": "ball",
                "position": [
                    -1515.3999864150883,
                    -21.51882815804884
                ],
                "id": 2511337692464,
                "mass": 1.0,
                "radius": 9.0,
                "color": "RED",
                "velocity": [
                    -116.48478812853972,
                    -10.139919430898445
                ],
                "acceleration": [
                    0,
                    98.1
                ]
            },
            {
                "type": "ball",
                "position": [
                    233.84251344174334,
                    -25.722645526545126
                ],
                "id": 2511337503296,
                "mass": 1.0,
                "radius": 9.0,
                "color": "RED",
                "velocity": [
                    6.478965022864038,
                    -27.710480151964227
                ],
                "acceleration": [
                    0,
                    98.1
                ]
            },
            {
                "type": "ball",
                "position": [
                    1116.3613179188349,
                    -36.652332912771456
                ],
                "id": 2511337698512,
                "mass": 1.0,
                "radius": 9.0,
                "color": "RED",
                "velocity": [
                    -8.735081381353067,
                    -3.96579376262519
                ],
                "acceleration": [
                    0,
                    98.1
                ]
            },
            {
                "type": "ball",
                "position": [
                    -1864.50188304569,
                    -24.66370977298904
                ],
                "id": 2511337557408,
                "mass": 1.0,
                "radius": 9.0,
                "color": "RED",
                "velocity": [
                    -134.38796668612133,
                    -39.961628311883906
                ],
                "acceleration": [
                    0,
                    98.1
                ]
            },
            {
                "type": "ball",
                "position": [
                    3059.3682211573732,
                    -56.679346383742974
                ],
                "id": 2511337495616,
                "mass": 1.0,
                "radius": 9.0,
                "color": "RED",
                "velocity": [
                    165.70767936651484,
                    57.348562228790314
                ],
                "acceleration": [
                    0,
                    98.1
                ]
            },
            {
                "type": "ball",
                "position": [
                    498.4438400634486,
                    -68.17664937941763
                ],
                "id": 2511337503200,
                "mass": 1.0,
                "radius": 9.0,
                "color": "RED",
                "velocity": [
                    53.919123641621695,
                    73.75321860626148
                ],
                "acceleration": [
                    0,
                    98.1
                ]
            },
            {
                "type": "ball",
                "position": [
                    -4365.513312033677,
                    -51.8668883844686
                ],
                "id": 2511337694624,
                "mass": 1.0,
                "radius": 9.0,
                "color": "RED",
                "velocity": [
                    -278.97776631588243,
                    94.32435631368867
                ],
                "acceleration": [
                    0,
                    98.1
                ]
            },
            {
                "type": "ball",
                "position": [
                    3915.7915714515266,
                    -19.000138553242795
                ],
                "id": 2511337701152,
                "mass": 1.0,
                "radius": 9.0,
                "color": "RED",
                "velocity": [
                    215.36028591666272,
                    -1.1643255983109513
                ],
                "acceleration": [
                    0,
                    98.1
                ]
            },
            {
                "type": "ball",
                "position": [
                    -5665.886345378191,
                    -19.109080232533312
                ],
                "id": 2511337695152,
                "mass": 1.0,
                "radius": 9.0,
                "color": "RED",
                "velocity": [
                    -325.2327851910262,
                    77.88235815268958
                ],
                "acceleration": [
                    0,
                    98.1
                ]
            },
            {
                "type": "ball",
                "position": [
                    1326.4161713917674,
                    -68.28032508293929
                ],
                "id": 2511337700672,
                "mass": 1.0,
                "radius": 9.0,
                "color": "RED",
                "velocity": [
                    29.35888810515758,
                    66.77493749644232
                ],
                "acceleration": [
                    0,
                    98.1
                ]
            },
            {
                "type": "ball",
                "position": [
                    -1201.4314004654607,
                    -115.55832117878592
                ],
                "id": 2511337504352,
                "mass": 1.0,
                "radius": 9.0,
                "color": "RED",
                "velocity": [
                    -95.79053792690344,
                    30.264593854626682
                ],
                "acceleration": [
                    0,
                    98.1
                ]
            },
            {
                "type": "ball",
                "position": [
                    -710.5609783406411,
                    -20.689711766614394
                ],
                "id": 2511337698368,
                "mass": 1.0,
                "radius": 9.0,
                "color": "RED",
                "velocity": [
                    -56.20442537367176,
                    49.40236965752738
                ],
                "acceleration": [
                    0,
                    98.1
                ]
            },
            {
                "type": "ball",
                "position": [
                    5419.473820566306,
                    -32.36468514572517
                ],
                "id": 2511337695920,
                "mass": 1.0,
                "radius": 9.0,
                "color": "RED",
                "velocity": [
                    338.2105442811088,
                    -9.971083546806884
                ],
                "acceleration": [
                    0,
                    98.1
                ]
            },
            {
                "type": "ball",
                "position": [
                    -639.3010917846811,
                    -180.68337624462623
                ],
                "id": 2511337700912,
                "mass": 1.0,
                "radius": 9.0,
                "color": "RED",
                "velocity": [
                    -77.61618140015077,
                    17.697732254862114
                ],
                "acceleration": [
                    0,
                    98.1
                ]
            },
            {
                "type": "ball",
                "position": [
                    -214.81872398538232,
                    -31.149441475973344
                ],
                "id": 2511337502336,
                "mass": 1.0,
                "radius": 9.0,
                "color": "RED",
                "velocity": [
                    11.581128023387969,
                    -113.24594362875281
                ],
                "acceleration": [
                    0,
                    98.1
                ]
            },
            {
                "type": "ball",
                "position": [
                    17.73764907278152,
                    -97.48194106185895
                ],
                "id": 2511337693808,
                "mass": 1.0,
                "radius": 9.0,
                "color": "RED",
                "velocity": [
                    16.303118722939164,
                    2.3919115461938247
                ],
                "acceleration": [
                    0,
                    98.1
                ]
            },
            {
                "type": "ball",
                "position": [
                    27.354527942726698,
                    -21.547496446073687
                ],
                "id": 2511337695248,
                "mass": 1.0,
                "radius": 9.0,
                "color": "RED",
                "velocity": [
                    -32.14203766983569,
                    -2.5768707885833124
                ],
                "acceleration": [
                    0,
                    98.1
                ]
            },
            {
                "type": "ball",
                "position": [
                    494.53355894546326,
                    -102.77753981296715
                ],
                "id": 2511337697888,
                "mass": 1.0,
                "radius": 9.0,
                "color": "RED",
                "velocity": [
                    -15.18005166603595,
                    31.767267334702826
                ],
                "acceleration": [
                    0,
                    98.1
                ]
            },
            {
                "type": "ball",
                "position": [
                    1112.229715424814,
                    -95.92324006835929
                ],
                "id": 2511337695872,
                "mass": 1.0,
                "radius": 9.0,
                "color": "RED",
                "velocity": [
                    172.1571350259388,
                    6.163557501942845
                ],
                "acceleration": [
                    0,
                    98.1
                ]
            },
            {
                "type": "ball",
                "position": [
                    -1348.0797978001076,
                    -50.83892453537731
                ],
                "id": 2511337498208,
                "mass": 1.0,
                "radius": 9.0,
                "color": "RED",
                "velocity": [
                    -132.36248073040528,
                    -66.75717649348968
                ],
                "acceleration": [
                    0,
                    98.1
                ]
            },
            {
                "type": "ball",
                "position": [
                    1196.7474182735455,
                    -41.759771881430986
                ],
                "id": 2511337497728,
                "mass": 1.0,
                "radius": 9.0,
                "color": "RED",
                "velocity": [
                    110.04190246391204,
                    -41.570041818063515
                ],
                "acceleration": [
                    0,
                    98.1
                ]
            },
            {
                "type": "ball",
                "position": [
                    -373.8774030095394,
                    -20.07935691789559
                ],
                "id": 2511337699952,
                "mass": 1.0,
                "radius": 9.0,
                "color": "RED",
                "velocity": [
                    21.738906813289685,
                    1.9219799125428612
                ],
                "acceleration": [
                    0,
                    98.1
                ]
            },
            {
                "type": "ball",
                "position": [
                    -88.8929309624778,
                    -27.45326226673533
                ],
                "id": 2511337698080,
                "mass": 1.0,
                "radius": 9.0,
                "color": "RED",
                "velocity": [
                    -19.88025801301731,
                    -18.26705799158971
                ],
                "acceleration": [
                    0,
                    98.1
                ]
            },
            {
                "type": "ball",
                "position": [
                    3631.838856757612,
                    -37.46614688435452
                ],
                "id": 2511337699760,
                "mass": 1.0,
                "radius": 9.0,
                "color": "RED",
                "velocity": [
                    154.00992057189498,
                    -74.87793108722043
                ],
                "acceleration": [
                    0,
                    98.1
                ]
            },
            {
                "type": "ball",
                "position": [
                    -2167.497589769505,
                    -129.9280242953563
                ],
                "id": 2511337700144,
                "mass": 1.0,
                "radius": 9.0,
                "color": "RED",
                "velocity": [
                    -135.6172018125447,
                    64.05882759966191
                ],
                "acceleration": [
                    0,
                    98.1
                ]
            },
            {
                "type": "ball",
                "position": [
                    -1676.6892334091608,
                    -33.14906100105982
                ],
                "id": 2511337698416,
                "mass": 1.0,
                "radius": 9.0,
                "color": "RED",
                "velocity": [
                    -121.77220151152699,
                    125.36573696606652
                ],
                "acceleration": [
                    0,
                    98.1
                ]
            },
            {
                "type": "ball",
                "position": [
                    186.61813309339075,
                    -130.68572721909155
                ],
                "id": 2511337632160,
                "mass": 1.0,
                "radius": 9.0,
                "color": "RED",
                "velocity": [
                    114.3551309514789,
                    -101.71332614523158
                ],
                "acceleration": [
                    0,
                    98.1
                ]
            },
            {
                "type": "ball",
                "position": [
                    209.90235894376775,
                    -81.1139915324189
                ],
                "id": 2511337697456,
                "mass": 1.0,
                "radius": 9.0,
                "color": "RED",
                "velocity": [
                    40.045779287828715,
                    30.274478042421208
                ],
                "acceleration": [
                    0,
                    98.1
                ]
            },
            {
                "type": "ball",
                "position": [
                    46.377884146638806,
                    -87.42588222926267
                ],
                "id": 2511337547696,
                "mass": 1.0,
                "radius": 9.0,
                "color": "RED",
                "velocity": [
                    45.608470172927746,
                    37.45138293717026
                ],
                "acceleration": [
                    0,
                    98.1
                ]
            }
        ],
        "wall": [],
        "rope": [],
        "spring": [],
        "rod": []
    }
}